{
  "$schema": "https://mintlify.com/docs.json",
  "theme": "mint",
  "name": "traxy docs",
  "colors": {
    "primary": "#B59ADB",
    "light": "#FFA7B3",
    "dark": "#685BFF"
  },
  "favicon": "/favicon.svg",
  "logo": {
    "light": "/logo/light.svg",
    "dark": "/logo/dark.svg"
  },
  "navigation": {
    "groups": [
      {
        "group": "Getting started",
        "pages": [
          "index",
          "quickstart",
          "getting-started/define-your-icp",
          "getting-started/join-a-workspace"
        ]
      },
      {
        "group": "Using traxy",
        "pages": [
          "using-traxy/dashboard",
          "using-traxy/icp-configuration",
          "using-traxy/leads",
          "using-traxy/content-calendar",
          "using-traxy/integrations",
          "using-traxy/workspace-and-team",
          "using-traxy/billing-and-credits",
          "using-traxy/usage-based-credits"
        ]
      },
      {
        "group": "Outbound playbooks",
        "pages": [
          "using-traxy/outbound-to-signal-based-leads",
          "using-traxy/signal-cheat-sheet",
          "using-traxy/outbound-playbook-content-led",
          "using-traxy/outbound-playbook-saas",
          "using-traxy/outbound-playbook-agencies",
          "using-traxy/outbound-playbook-events"
        ]
      },
      {
        "group": "Troubleshooting",
        "pages": [
          "troubleshooting/no-qualified-leads-yet",
          "troubleshooting/faq"
        ]
      }
    ]
  },
  "navbar": {
    "links": [
      {
        "label": "Support",
        "href": "mailto:support@traxy.ai"
      }
    ]
  }
}
